README.md
setup.py
RareDecipher/__init__.py
RareDecipher/deconvolution.py
RareDecipher/runDecipher.py
RareDecipher.egg-info/PKG-INFO
RareDecipher.egg-info/SOURCES.txt
RareDecipher.egg-info/dependency_links.txt
RareDecipher.egg-info/requires.txt
RareDecipher.egg-info/top_level.txt